sfapi_client/__init__.py
sfapi_client/_compute.py
sfapi_client/_jobs.py
sfapi_client/_monitor.py
sfapi_client/_utils.py
sfapi_client/client.py
sfapi_client/compute.py
sfapi_client/exceptions.py
sfapi_client/groups.py
sfapi_client/jobs.py
sfapi_client/paths.py
sfapi_client/projects.py
sfapi_client/resources.py
sfapi_client/users.py
sfapi_client/_async/__init__.py
sfapi_client/_async/client.py
sfapi_client/_async/compute.py
sfapi_client/_async/groups.py
sfapi_client/_async/jobs.py
sfapi_client/_async/paths.py
sfapi_client/_async/projects.py
sfapi_client/_async/users.py
sfapi_client/_models/__init__.py
sfapi_client/_models/job_status_response_sacct.py
sfapi_client/_models/job_status_response_squeue.py
sfapi_client/_models/resources.py
sfapi_client/_sync/__init__.py
sfapi_client/_sync/client.py
sfapi_client/_sync/compute.py
sfapi_client/_sync/groups.py
sfapi_client/_sync/jobs.py
sfapi_client/_sync/paths.py
sfapi_client/_sync/projects.py
sfapi_client/_sync/users.py
sfapi_client-0.4.1.dist-info/METADATA
sfapi_client-0.4.1.dist-info/WHEEL
sfapi_client-0.4.1.dist-info/licenses/LICENSE
sfapi_client-0.4.1.dist-info/RECORD
