Metadata-Version: 2.4
Name: sfapi_client
Version: 0.4.1
Summary: Python client for NERSC SF API
Author-email: Chris Harris <cjh@lbl.gov>, Nicholas Tyler <tylern@lbl.gov>
License-File: LICENSE
Classifier: License :: OSI Approved :: BSD License
Classifier: Operating System :: OS Independent
Classifier: Programming Language :: Python :: 3
Requires-Python: >=3.7
Requires-Dist: authlib
Requires-Dist: httpx
Requires-Dist: pydantic-settings
Requires-Dist: pydantic~=2.0
Requires-Dist: tenacity
Provides-Extra: docs
Requires-Dist: mkdocs-gen-files; extra == 'docs'
Requires-Dist: mkdocs-jupyter; extra == 'docs'
Requires-Dist: mkdocs-literate-nav; extra == 'docs'
Requires-Dist: mkdocs-material; extra == 'docs'
Requires-Dist: mkdocs-section-index; extra == 'docs'
Requires-Dist: mkdocstrings[python]; extra == 'docs'
Provides-Extra: test
Requires-Dist: pydantic[dotenv]; extra == 'test'
Requires-Dist: pytest; extra == 'test'
Requires-Dist: pytest-asyncio; extra == 'test'
Requires-Dist: pytest-mock; extra == 'test'
